flowable/__init__.py
flowable/external_worker_client/__init__.py
flowable/external_worker_client/cloud_token.py
flowable/external_worker_client/engine_rest_variable.py
flowable/external_worker_client/external_worker_acquire_job_response.py
flowable/external_worker_client/external_worker_job_response.py
flowable/external_worker_client/flowable_rest_exception.py
flowable/external_worker_client/list_result.py
flowable/external_worker_client/request_converter.py
flowable/external_worker_client/response_converter.py
flowable/external_worker_client/restclient.py
flowable/external_worker_client/utils.py
flowable/external_worker_client/worker_result.py
flowable.external_worker_client-1.0.2.dist-info/METADATA
flowable.external_worker_client-1.0.2.dist-info/WHEEL
flowable.external_worker_client-1.0.2.dist-info/top_level.txt
flowable.external_worker_client-1.0.2.dist-info/RECORD
