Metadata-Version: 2.1
Name: flowable.external-worker-client
Version: 1.0.2
Summary: Flowable External Worker Library to connect Python code to Flowable using an external worker.
Author: Flowable
License: Apache License, Version 2.0
Requires-Dist: requests>=2.27.0
Provides-Extra: testing
Requires-Dist: pytest; extra == "testing"
Requires-Dist: vcrpy; extra == "testing"
